chatgptdevfriendly/__init__.py
chatgptdevfriendly/v1.py
chatgptdevfriendly-1.0.0.dist-info/METADATA
chatgptdevfriendly-1.0.0.dist-info/WHEEL
chatgptdevfriendly-1.0.0.dist-info/licenses/LICENSE.txt
chatgptdevfriendly-1.0.0.dist-info/RECORD
