Metadata-Version: 2.1
Name: chatgptdevfriendly
Version: 1.0.0
Summary: A wrapper package which takes care of API call robustness to ensure developers quickly and easily develop CHatGPT based applications.
Project-URL: Homepage, https://github.com/codeastra2/ChatGPTDevFriendly
Author-email: Srinivas Kumar R <srinivas1996kumar@gmail.com>
License-File: LICENSE.txt
Classifier: License :: OSI Approved :: MIT License
Classifier: Operating System :: OS Independent
Classifier: Programming Language :: Python :: 3
Requires-Python: >=3.7
Requires-Dist: matplotlib==3.7.1
Requires-Dist: openai==0.27.4
Requires-Dist: requests
